{"theme":"jobs","category":"clothing","subtype":"shirts","page":1,"pageSize":30,"total":3,"items":[{"taxonomyName":["Shirt"],"id":16495186173,"assetType":65,"name":"Delinquent Top (Black)","creatorName":"Luka's Workshop","price":60,"favoriteCount":8084,"itemRestrictions":[],"foundByCategoryFilter":"None","dateCreated":"2024-02-24T00:40:03.507Z","isBundle":false,"themes":["angelcore","barbie","casual","clean","cutecore","dark","eboy","emo","formal","girly","grunge","gyaru","jobs","kawaii","light","milk","preppy","punk","scene","simple","softgirl","softie","uke","villain","y2k","yabujin"]},{"taxonomyName":["Shirt"],"id":18469856540,"assetType":65,"name":"Vested School Uniform Top Danger","creatorName":"BEASTinWHITE","price":60,"favoriteCount":4412,"itemRestrictions":[],"foundByCategoryFilter":"None","dateCreated":"2024-07-13T12:36:33.88Z","isBundle":false,"themes":["angelcore","cowboy","jobs","light","milk","monster","royalty","softie"]},{"taxonomyName":["Shirt"],"id":121272036982619,"assetType":65,"name":"Neymar Polo Uniform (Brazil)","creatorName":"VoxWorks UGC","price":60,"favoriteCount":987,"itemRestrictions":[],"foundByCategoryFilter":"None","dateCreated":"2026-01-07T18:15:47.32Z","isBundle":false,"themes":["cutecore","girly","jobs","softie"]}]}