{"page":166,"pageSize":30,"total":14837,"items":[{"id":9349740828,"name":"White Striped Sport Shorts","category":"clothing","subtype":"shorts","keywords":[],"favoriteCount":174,"isRobloxOfficial":false,"page":null},{"id":76424602979516,"name":"☆ Cute shoujo beach hairstyle black","category":"body","subtype":"hair","keywords":[],"favoriteCount":174,"isRobloxOfficial":false,"page":null},{"id":18359025046,"name":"✅ Pink shorts ✅","category":"clothing","subtype":"shorts","keywords":[],"favoriteCount":174,"isRobloxOfficial":false,"page":null},{"id":125477479537083,"name":"(Black and Purple) Striped Scarf","category":"accessories","subtype":"neck","keywords":[],"favoriteCount":173,"isRobloxOfficial":false,"page":null},{"id":18497032562,"name":"[-₩-] Memory Cloth Cape V.1","category":"accessories","subtype":"back","keywords":[],"favoriteCount":173,"isRobloxOfficial":false,"page":null},{"id":18754724657,"name":"BackPack","category":"accessories","subtype":"back","keywords":[],"favoriteCount":173,"isRobloxOfficial":false,"page":null},{"id":13885067368,"name":"Beanie","category":"accessories","subtype":"hats","keywords":[],"favoriteCount":173,"isRobloxOfficial":false,"page":null},{"id":104254080886817,"name":"Biggest Bundle","category":"bundles","subtype":"all","keywords":[],"favoriteCount":173,"isRobloxOfficial":false,"page":null},{"id":113353236603581,"name":"Cold Face White Beanie","category":"accessories","subtype":"hats","keywords":[],"favoriteCount":173,"isRobloxOfficial":false,"page":null},{"id":17099970960,"name":"Cute Trendy Red Skirt","category":"clothing","subtype":"dressskirts","keywords":[],"favoriteCount":173,"isRobloxOfficial":false,"page":null},{"id":157480117732159,"name":"Dynamic Werewolf Head","category":"body","subtype":"heads","keywords":[],"favoriteCount":173,"isRobloxOfficial":false,"page":null},{"id":640598,"name":"Monkey King Wukong Bundle","category":"bundles","subtype":"all","keywords":[],"favoriteCount":173,"isRobloxOfficial":false,"page":null},{"id":11893402303,"name":"Mushroom Stickers - Blue","category":"accessories","subtype":"face","keywords":[],"favoriteCount":173,"isRobloxOfficial":false,"page":null},{"id":1268595,"name":"Porg Owl Bundle","category":"bundles","subtype":"all","keywords":[],"favoriteCount":173,"isRobloxOfficial":false,"page":null},{"id":5530,"name":"Red Seriously Frog Meme Head","category":"body","subtype":"heads","keywords":[],"favoriteCount":173,"isRobloxOfficial":false,"page":null},{"id":85382565048221,"name":"♡ dynamic vkei jirai kei cute sleepy big dark eyes","category":"body","subtype":"heads","keywords":[],"favoriteCount":173,"isRobloxOfficial":false,"page":null},{"id":12849849288,"name":"😊 Beanie 😊","category":"accessories","subtype":"hats","keywords":[],"favoriteCount":173,"isRobloxOfficial":false,"page":null},{"id":139507124117293,"name":"backpack holding idle pose","category":"animations","subtype":"emotes","keywords":[],"favoriteCount":172,"isRobloxOfficial":false,"page":null},{"id":88740245595523,"name":"Black Medieval Cape","category":"accessories","subtype":"back","keywords":[],"favoriteCount":172,"isRobloxOfficial":false,"page":null},{"id":15882981688,"name":"brown sneaker shoes","category":"clothing","subtype":"shoes","keywords":[],"favoriteCount":172,"isRobloxOfficial":false,"page":null},{"id":111861689628315,"name":"Buffalo Rainbow Knit Sweater","category":"clothing","subtype":"sweaters","keywords":[],"favoriteCount":172,"isRobloxOfficial":false,"page":null},{"id":130042819914749,"name":"Builders Club","category":"accessories","subtype":"hats","keywords":[],"favoriteCount":172,"isRobloxOfficial":false,"page":null},{"id":78856750592709,"name":"Cute Kawaii Bunny Spirit Shoulder Pet Friend White","category":"accessories","subtype":"shoulder","keywords":[],"favoriteCount":172,"isRobloxOfficial":false,"page":null},{"id":17342444951,"name":"doll skirt","category":"clothing","subtype":"dressskirts","keywords":[],"favoriteCount":172,"isRobloxOfficial":false,"page":null},{"id":14765571640,"name":"Durable Boots","category":"clothing","subtype":"shoes","keywords":[],"favoriteCount":172,"isRobloxOfficial":false,"page":null},{"id":17505667337,"name":"Gregorio","category":"accessories","subtype":"hats","keywords":[],"favoriteCount":172,"isRobloxOfficial":false,"page":null},{"id":15358967431,"name":"Intergalactic Batter Buddy","category":"accessories","subtype":"hats","keywords":[],"favoriteCount":172,"isRobloxOfficial":false,"page":null},{"id":129396357692837,"name":"Make Heart Shape (Only woman package)","category":"bundles","subtype":"all","keywords":[],"favoriteCount":172,"isRobloxOfficial":false,"page":null},{"id":101223564961870,"name":"Metal Leather Goggles","category":"accessories","subtype":"face","keywords":[],"favoriteCount":172,"isRobloxOfficial":false,"page":null},{"id":137622956938639,"name":"Retro/Vintage Boots | Pink Leopard","category":"clothing","subtype":"shoes","keywords":[],"favoriteCount":172,"isRobloxOfficial":false,"page":null}]}