{"page":307,"pageSize":30,"total":22155,"items":[{"id":18745211803,"name":"Gyaru ♡ ギャル lush drag wig (blonde)","category":"body","subtype":"hair","keywords":[],"page":null},{"id":18745158688,"name":"Gyaru ♡ ギャル lush drag wig (Choco-berry🍓)","category":"body","subtype":"hair","keywords":[],"page":null},{"id":18745073167,"name":"Gyaru ♡ ギャル lush drag wig (ginger-berry)","category":"body","subtype":"hair","keywords":[],"page":null},{"id":18744938399,"name":"Gyaru ♡ ギャル lush drag wig (hot pink)","category":"body","subtype":"hair","keywords":[],"page":null},{"id":18745274905,"name":"Gyaru ♡ ギャル lush drag wig (rose)","category":"body","subtype":"hair","keywords":[],"page":null},{"id":18745117121,"name":"Gyaru ♡ ギャル lush drag wig (Vanilla-berry🍦)","category":"body","subtype":"hair","keywords":[],"page":null},{"id":135256965967670,"name":"Gyaru/Gal Leather Tote bag (Broken)","category":"accessories","subtype":"front","keywords":[],"page":null},{"id":139081699841204,"name":"Gymskin Dance","category":"animations","subtype":"emotes","keywords":[],"page":null},{"id":18397506883,"name":"Gyomei Himejima [-]","category":"clothing","subtype":"pants","keywords":[],"page":null},{"id":90337088597533,"name":"H.E.R.B.I.E Shoulder Companion","category":"accessories","subtype":"shoulder","keywords":[],"page":null},{"id":111798780094375,"name":"H.S.K.T dance (right)","category":"animations","subtype":"emotes","keywords":[],"page":null},{"id":12025047943,"name":"H.U.N.T. Operative Helmet","category":"accessories","subtype":"hats","keywords":[],"page":null},{"id":74171707858814,"name":"Hacher2296 shoulder pet","category":"accessories","subtype":"shoulder","keywords":[],"page":null},{"id":114309333719248,"name":"Hacker Cape","category":"accessories","subtype":"back","keywords":[],"page":null},{"id":113028296660751,"name":"hahahahjsbs","category":"clothing","subtype":"tshirts","keywords":[],"page":null},{"id":81208929953910,"name":"Hair","category":"body","subtype":"hair","keywords":[],"page":null},{"id":78383503830906,"name":"Hair","category":"body","subtype":"hair","keywords":[],"page":null},{"id":124816117915378,"name":"Hair","category":"body","subtype":"hair","keywords":[],"page":null},{"id":135591956561187,"name":"Hair ","category":"body","subtype":"hair","keywords":[],"page":null},{"id":139662317868578,"name":"Hair","category":"body","subtype":"hair","keywords":[],"page":null},{"id":95878162535022,"name":"Hair","category":"body","subtype":"hair","keywords":[],"page":null},{"id":13843310808,"name":"Hair","category":"body","subtype":"hair","keywords":[],"page":null},{"id":13883988942,"name":"Hair","category":"body","subtype":"hair","keywords":[],"page":null},{"id":84520259774275,"name":"Hair","category":"body","subtype":"hair","keywords":[],"page":null},{"id":17376374231,"name":"Hair","category":"body","subtype":"hair","keywords":[],"page":null},{"id":80772935755760,"name":"Hair ","category":"body","subtype":"hair","keywords":[],"page":null},{"id":84306623978209,"name":"Hair","category":"body","subtype":"hair","keywords":[],"page":null},{"id":75407968701410,"name":"Hair","category":"body","subtype":"hair","keywords":[],"page":null},{"id":18221932846,"name":"Hair","category":"body","subtype":"hair","keywords":[],"page":null},{"id":110386765520527,"name":"Hair Braids","category":"body","subtype":"hair","keywords":[],"page":null}]}