{"page":294,"pageSize":30,"total":22155,"items":[{"id":110169320316279,"name":"Gothitelle dress","category":"clothing","subtype":"dressskirts","keywords":[],"page":null},{"id":120625834593457,"name":"Goyar Burgundy Duffel Bag 1.0","category":"accessories","subtype":"waist","keywords":[],"page":null},{"id":16636267460,"name":"Gradient Rhinestone Stunna Lock Boots | Black","category":"clothing","subtype":"shoes","keywords":[],"page":null},{"id":14751920911,"name":"Graffiti Bag","category":"accessories","subtype":"front","keywords":[],"page":null},{"id":119317650282350,"name":"Graipusini","category":"accessories","subtype":"back","keywords":[],"page":null},{"id":114934237825542,"name":"Grape Splash Vizor","category":"accessories","subtype":"face","keywords":[],"page":null},{"id":13620712225,"name":"graph's Pal","category":"accessories","subtype":"shoulder","keywords":[],"page":null},{"id":72417957232821,"name":"Graphic Print Pleated Skirt","category":"clothing","subtype":"dressskirts","keywords":[],"page":null},{"id":15654405595,"name":"Gravity Potion","category":"clothing","subtype":"tshirts","keywords":[],"page":null},{"id":91342087341042,"name":"Gray & White Streetwear Shoes","category":"clothing","subtype":"shoes","keywords":[],"page":null},{"id":124876305352555,"name":"Gray American Shorthair Kemono Head (Star Eyes)","category":"body","subtype":"heads","keywords":[],"page":null},{"id":12377265672,"name":"Gray and Brown Fluffy Ushanka","category":"accessories","subtype":"hats","keywords":[],"page":null},{"id":74823251779689,"name":"Gray Archival Vkei Bead Rope Belt","category":"accessories","subtype":"waist","keywords":[],"page":null},{"id":139848620680497,"name":"Gray Beard","category":"makeup","subtype":"all","keywords":[],"page":null},{"id":125180926102986,"name":"Gray Big Cross Necklace","category":"accessories","subtype":"neck","keywords":[],"page":null},{"id":84662074899460,"name":" Gray Crocodile Birkin Chic Designer Bag","category":"accessories","subtype":"front","keywords":[],"page":null},{"id":16137133956,"name":"Gray Devil hunter trench coat","category":"clothing","subtype":"jackets","keywords":[],"page":null},{"id":6902238115,"name":"Gray Elephant Plush","category":"accessories","subtype":"waist","keywords":[],"page":null},{"id":73271183814775,"name":"Gray Eyebrows","category":"makeup","subtype":"all","keywords":[],"page":null},{"id":273513967681101,"name":"Gray Heels","category":"clothing","subtype":"shoes","keywords":[],"page":null},{"id":4933290246,"name":"Gray Helmet","category":"accessories","subtype":"hats","keywords":[],"page":null},{"id":17024218238,"name":"Gray Hoodie","category":"clothing","subtype":"sweaters","keywords":[],"page":null},{"id":122744607970721,"name":"Gray Hoodie with Ski Mask","category":"clothing","subtype":"sweaters","keywords":[],"page":null},{"id":18970379781,"name":"gray jeans w balecis","category":"clothing","subtype":"pants","keywords":[],"page":null},{"id":16460773906,"name":"Gray Laces Heart Bag","category":"accessories","subtype":"front","keywords":[],"page":null},{"id":77869432622515,"name":"Gray Leopard Tail","category":"accessories","subtype":"waist","keywords":[],"page":null},{"id":92789342400063,"name":"gray lipstick","category":"makeup","subtype":"all","keywords":[],"page":null},{"id":109367843482104,"name":"gray lipstick","category":"makeup","subtype":"all","keywords":[],"page":null},{"id":11645119365,"name":"Gray Matching Blueberry Sui","category":"clothing","subtype":"pants","keywords":[],"page":null},{"id":15984468099,"name":"Gray No Cap Y2K Cap","category":"accessories","subtype":"hats","keywords":[],"page":null}]}