{"page":785,"pageSize":30,"total":27315,"items":[{"id":86180797797589,"name":"White Blazer w/ Black Turtleneck","category":"clothing","subtype":"jackets","keywords":[],"page":null},{"id":91496247014873,"name":"White Blazer w/ Shirt & Tie","category":"clothing","subtype":"jackets","keywords":[],"page":null},{"id":133777068207963,"name":"White Blazer w/ White Turtleneck","category":"clothing","subtype":"jackets","keywords":[],"page":null},{"id":12600156456,"name":"White bone heart necklace 1.0","category":"accessories","subtype":"neck","keywords":[],"page":null},{"id":12600169919,"name":"White bone heart necklace 3.0","category":"accessories","subtype":"neck","keywords":[],"page":null},{"id":90789985314937,"name":"White Breacher Tactical Vest","category":"accessories","subtype":"front","keywords":[],"page":null},{"id":85282680486760,"name":"White Bridal Skirt","category":"clothing","subtype":"dressskirts","keywords":[],"page":null},{"id":106584533209052,"name":"White Bronze Plated Roman Musculata Cape","category":"accessories","subtype":"back","keywords":[],"page":null},{"id":9399982215,"name":"White Brooklyn Crewneck Jumper","category":"clothing","subtype":"sweaters","keywords":[],"page":null},{"id":136916134167720,"name":"White Business Pants & Blazer","category":"clothing","subtype":"jackets","keywords":[],"page":null},{"id":89075682471939,"name":"White Business Pants & Open Blazer","category":"clothing","subtype":"jackets","keywords":[],"page":null},{"id":9844440666,"name":"White Business Tuxedo Blazer","category":"clothing","subtype":"jackets","keywords":[],"page":null},{"id":5275347940,"name":"White button crop top","category":"clothing","subtype":"shirts","keywords":[],"page":null},{"id":10507717098,"name":"White Button Shirt ","category":"clothing","subtype":"shirts","keywords":[],"page":null},{"id":8603789629,"name":"White Button Shirt","category":"clothing","subtype":"shirts","keywords":[],"page":null},{"id":5207409731,"name":"white button shirt","category":"clothing","subtype":"shirts","keywords":[],"page":null},{"id":15890476383,"name":"white button shirt suit [female ver, long sleeve]","category":"clothing","subtype":"shirts","keywords":[],"page":null},{"id":15890188958,"name":"white button shirt tie [female version]","category":"clothing","subtype":"shirts","keywords":[],"page":null},{"id":6563899434,"name":"white button top","category":"clothing","subtype":"shirts","keywords":[],"page":null},{"id":5963633577,"name":"White Button Top","category":"clothing","subtype":"shirts","keywords":[],"page":null},{"id":5247371810,"name":"white button top","category":"clothing","subtype":"shirts","keywords":[],"page":null},{"id":5165849401,"name":"white button top (2)","category":"clothing","subtype":"shirts","keywords":[],"page":null},{"id":5317751566,"name":"White Button Top Ribbed","category":"clothing","subtype":"shirts","keywords":[],"page":null},{"id":5159891243,"name":"White Button Up Blouse brnw ext","category":"clothing","subtype":"shirts","keywords":[],"page":null},{"id":8064426471,"name":"White button up cardi top | light academia","category":"clothing","subtype":"shirts","keywords":[],"page":null},{"id":5611025501,"name":"white button up crop top","category":"clothing","subtype":"shirts","keywords":[],"page":null},{"id":14626675979,"name":"white button up dropdown s","category":"clothing","subtype":"shirts","keywords":[],"page":null},{"id":10503221224,"name":"White button up shirt","category":"clothing","subtype":"shirts","keywords":[],"page":null},{"id":6409468972,"name":"White Button Up Top","category":"clothing","subtype":"shirts","keywords":[],"page":null},{"id":4938587890,"name":"White Button Up Top","category":"clothing","subtype":"shirts","keywords":[],"page":null}]}