{"theme":"light","category":"accessories","subtype":"front-accessory","page":2,"pageSize":30,"total":215,"items":[{"taxonomyName":["Front Accessories"],"id":91660469604072,"assetType":45,"name":"Red Rose Vintage Lapel Pin With Silver Chains","creatorName":"Szeloba","price":50,"favoriteCount":18396,"itemRestrictions":[],"foundByCategoryFilter":"None","dateCreated":"2025-04-25T18:29:15.097Z","isBundle":false,"themes":["angelcore","coquette","dark","eboy","emo","grunge","indiecore","light","metal","milk","punk","rich","rogangster","scene","softie","villain","vintage"]},{"taxonomyName":["Front Accessories"],"id":16290596944,"assetType":45,"name":"Earbuds v2","creatorName":"yumari","price":50,"favoriteCount":17413,"itemRestrictions":[],"foundByCategoryFilter":"None","dateCreated":"2024-02-08T22:00:13.127Z","isBundle":false,"themes":["angelcore","light","milk","softie"]},{"taxonomyName":["Front Accessories"],"id":95994581887897,"assetType":45,"name":"gothic black top & white striped dress 3.0","creatorName":"our demise","price":50,"favoriteCount":16736,"itemRestrictions":[],"foundByCategoryFilter":"None","dateCreated":"2025-12-07T20:05:04.97Z","isBundle":false,"themes":["angelcore","dark","eboy","emo","formal","grunge","light","milk","softie","villain"]},{"taxonomyName":["Front Accessories"],"id":18110477536,"assetType":45,"name":"White Ribbon Simple Red Purse Christmas","creatorName":"Valkenheim UGC","price":50,"favoriteCount":16661,"itemRestrictions":[],"foundByCategoryFilter":"None","dateCreated":"2024-06-18T19:10:07.607Z","isBundle":false,"themes":["angelcore","barbie","casual","clean","dark","eboy","emo","girly","grunge","light","milk","preppy","seasonal","simple","softie","villain"]},{"taxonomyName":["Front Accessories"],"id":17073115934,"assetType":45,"name":"vstar* All over Puffer Vest V2 White ","creatorName":"vstar*","price":50,"favoriteCount":16465,"itemRestrictions":[],"foundByCategoryFilter":"None","dateCreated":"2024-04-09T00:04:00.56Z","isBundle":false,"themes":["angelcore","cowboy","light","milk","softie"]},{"taxonomyName":["Front Accessories"],"id":124320837487763,"assetType":45,"name":"˶˃ ᵕ ˂˶ cute NUM NOM shirt","creatorName":"nommis","price":50,"favoriteCount":15135,"itemRestrictions":[],"foundByCategoryFilter":"None","dateCreated":"2025-08-31T07:08:53.413Z","isBundle":false,"themes":["angelcore","anime","babycore","barbie","chibi","cutecore","cutegore","cybercore","dark","demon","dog","eboy","emo","fairy","food","formal","fox","furry","girly","grunge","kawaii","light","milk","mini","monster","neko","preppy","rainbowcore","scene","softgirl","softie","villain","yabujin"]},{"taxonomyName":["Front Accessories"],"id":17344501519,"assetType":45,"name":"White Purse","creatorName":"Valkenheim UGC","price":50,"favoriteCount":14369,"itemRestrictions":[],"foundByCategoryFilter":"None","dateCreated":"2024-05-01T01:46:52.61Z","isBundle":false,"themes":["angelcore","barbie","dark","eboy","emo","girly","grunge","light","milk","softie","villain"]},{"taxonomyName":["Front Accessories"],"id":17295917228,"assetType":45,"name":"Puffer Vest + Neck Fur Collar 1.0","creatorName":"Valkenheim UGC","price":60,"favoriteCount":14238,"itemRestrictions":[],"foundByCategoryFilter":"None","dateCreated":"2024-04-26T22:20:04.703Z","isBundle":false,"themes":["angelcore","cowboy","dark","eboy","emo","furry","grunge","light","milk","softie","villain","wolf"]},{"taxonomyName":["Front Accessories"],"id":72272975168802,"assetType":45,"name":"3.0 cute polka dot dress & bow collar - white","creatorName":"our demise","price":50,"favoriteCount":14158,"itemRestrictions":[],"foundByCategoryFilter":"None","dateCreated":"2025-11-17T23:19:48.573Z","isBundle":false,"themes":["angelcore","babycore","chibi","cutegore","formal","girly","kawaii","light","milk","mini","preppy","softgirl","softie"]},{"taxonomyName":["Front Accessories"],"id":89189634499576,"assetType":45,"name":"Victorian White Ruffle Jabot Red Rose ","creatorName":"Sevenly","price":50,"favoriteCount":14133,"itemRestrictions":[],"foundByCategoryFilter":"None","dateCreated":"2025-07-26T12:11:02.283Z","isBundle":false,"themes":["angelcore","light","lolita","milk","softie","steampunk"]},{"taxonomyName":["Front Accessories"],"id":16662520699,"assetType":45,"name":"Puffer Vest V2 Brown","creatorName":"Valkenheim UGC","price":50,"favoriteCount":13995,"itemRestrictions":[],"foundByCategoryFilter":"None","dateCreated":"2024-03-08T03:10:59.343Z","isBundle":false,"themes":["angelcore","cowboy","dark","eboy","emo","grunge","light","milk","softie","villain"]},{"taxonomyName":["Front Accessories"],"id":94029679344474,"assetType":45,"name":"Red Rose Vintage Lapel Pin With Golden Chains","creatorName":"idea.exe","price":50,"favoriteCount":13525,"itemRestrictions":[],"foundByCategoryFilter":"None","dateCreated":"2025-04-25T19:01:50.55Z","isBundle":false,"themes":["angelcore","coquette","dark","eboy","emo","grunge","indiecore","light","metal","milk","punk","rich","rogangster","scene","softie","villain","vintage"]},{"taxonomyName":["Front Accessories"],"id":128285967153246,"assetType":45,"name":"ʚ♡ɞcute flowy polka dot ruffled dress white & pink","creatorName":"lwu","price":50,"favoriteCount":13284,"itemRestrictions":[],"foundByCategoryFilter":"None","dateCreated":"2025-08-30T02:22:10.86Z","isBundle":false,"themes":["angelcore","babycore","barbie","bohemian","chibi","cutegore","formal","girly","kawaii","light","milk","mini","preppy","softgirl","softie"]},{"taxonomyName":["Front Accessories"],"id":135619076659405,"assetType":45,"name":"Green and Pink Floral Babydoll Dress ","creatorName":"~sweet • berrie~","price":50,"favoriteCount":12682,"itemRestrictions":[],"foundByCategoryFilter":"None","dateCreated":"2025-05-14T22:49:01.453Z","isBundle":false,"themes":["angelcore","barbie","coquette","cottagecore","dark","eboy","emo","formal","girly","grunge","gyaru","light","lolita","milk","softie","villain"]},{"taxonomyName":["Front Accessories"],"id":109061683713087,"assetType":45,"name":"Incense White Scarf Cowl","creatorName":"G A i A","price":50,"favoriteCount":12029,"itemRestrictions":[],"foundByCategoryFilter":"None","dateCreated":"2025-02-22T20:56:24.65Z","isBundle":false,"themes":["angelcore","light","milk","softie"]},{"taxonomyName":["Front Accessories"],"id":15703562799,"assetType":45,"name":"✅ Emo","creatorName":"REB3L","price":50,"favoriteCount":11996,"itemRestrictions":[],"foundByCategoryFilter":"None","dateCreated":"2023-12-21T18:05:29.75Z","isBundle":false,"themes":["academia","angelcore","anime","babycore","baddie","barbie","casual","chibi","clean","copyandpaste","coquette","cutecore","cutegore","cybercore","dahoodian","dark","drip","eboy","emo","fairy","formal","girly","glitchcore","grunge","gyaru","indiecore","kawaii","light","mini","neon","preppy","rogangster","scene","simple","skater","slender","softgirl","softie","streetwear","urban","villain","vintage","y2k","yabujin"]},{"taxonomyName":["Front Accessories"],"id":99426501919621,"assetType":45,"name":"Royal Rose Lace Corset in Pink (3.0)","creatorName":"~sweet • berrie~","price":50,"favoriteCount":11980,"itemRestrictions":[],"foundByCategoryFilter":"None","dateCreated":"2025-04-05T21:59:21.44Z","isBundle":false,"themes":["angelcore","barbie","coquette","dark","eboy","emo","girly","grunge","kawaii","light","lolita","milk","royalty","softie","villain"]},{"taxonomyName":["Front Accessories"],"id":90439748936627,"assetType":45,"name":"Epic Mystical Gothic Emo Distressed Scarf White","creatorName":"Only Costumes","price":50,"favoriteCount":11736,"itemRestrictions":[],"foundByCategoryFilter":"None","dateCreated":"2025-11-18T23:45:26.357Z","isBundle":false,"themes":["alien","angelcore","barbie","clown","cowboy","demon","dog","dragon","elf","emo","fairy","fantasy","knight","light","milk","monster","ninja","pirate","robot","royalty","softie","superhero","vampire","villain","whimsical","witch"]},{"taxonomyName":["Front Accessories"],"id":17044220688,"assetType":45,"name":"Ruffle Pillow White / Pink","creatorName":"Valkenheim UGC","price":50,"favoriteCount":11586,"itemRestrictions":[],"foundByCategoryFilter":"None","dateCreated":"2024-04-07T00:18:35.393Z","isBundle":false,"themes":["angelcore","barbie","dark","eboy","emo","girly","grunge","light","milk","softie","villain"]},{"taxonomyName":["Front Accessories"],"id":137777333633936,"assetType":45,"name":"Rough Steel Black Body And Neck Chains","creatorName":"Zentrix UGC","price":50,"favoriteCount":11520,"itemRestrictions":[],"foundByCategoryFilter":"None","dateCreated":"2024-12-05T02:42:54.643Z","isBundle":false,"themes":["angelcore","anime","barbie","casual","clean","cutecore","dahoodian","dark","dog","drip","eboy","emo","food","formal","girly","grunge","gyaru","jobs","kawaii","light","metal","milk","mini","neko","preppy","punk","rogangster","scene","seasonal","simple","softie","uke","villain","winter","y2k","yabujin"]},{"taxonomyName":["Front Accessories"],"id":74387995853513,"assetType":45,"name":"1.0 R6 Female Cropped Top","creatorName":"Solidz","price":67,"favoriteCount":11485,"itemRestrictions":[],"foundByCategoryFilter":"None","dateCreated":"2024-11-12T01:02:49.833Z","isBundle":false,"themes":["angelcore","dark","eboy","emo","formal","grunge","light","milk","r6","softie","villain"]},{"taxonomyName":["Front Accessories"],"id":82413791303625,"assetType":45,"name":"♡ : cute yellow polka dot dress","creatorName":"/interlace","price":50,"favoriteCount":11450,"itemRestrictions":[],"foundByCategoryFilter":"Recommended","dateCreated":"2026-03-16T23:21:49.126Z","isBundle":false,"themes":["babycore","barbie","chibi","coquette","cottagecore","cutecore","cutegore","dark","eboy","emo","fairy","formal","girly","grunge","kawaii","light","lolita","mini","neko","preppy","softgirl","softie","uke","villain"]},{"taxonomyName":["Front Accessories"],"id":17296139106,"assetType":45,"name":"White Puffer Vest + Neck Fur Collar 1.0","creatorName":"Valkenheim UGC","price":50,"favoriteCount":11054,"itemRestrictions":[],"foundByCategoryFilter":"None","dateCreated":"2024-04-26T22:50:21.547Z","isBundle":false,"themes":["angelcore","cowboy","dark","eboy","emo","furry","grunge","light","milk","softie","villain","wolf"]},{"taxonomyName":["Front Accessories"],"id":139407303845858,"assetType":45,"name":"gothic plaid ruffle dress w bow - black white","creatorName":"our demise","price":50,"favoriteCount":10835,"itemRestrictions":[],"foundByCategoryFilter":"None","dateCreated":"2025-10-02T19:26:50.277Z","isBundle":false,"themes":["angelcore","dark","eboy","emo","formal","girly","grunge","light","milk","softie","villain"]},{"taxonomyName":["Front Accessories"],"id":18332695671,"assetType":45,"name":"1.0 Crooked Heart Rib Cage (Black)","creatorName":"> F1SCH's EMPORIUM <","price":50,"favoriteCount":10617,"itemRestrictions":[],"foundByCategoryFilter":"None","dateCreated":"2024-07-04T15:32:48.89Z","isBundle":false,"themes":["angelcore","dark","eboy","emo","grunge","light","milk","softie","villain"]},{"taxonomyName":["Front Accessories"],"id":75955280723104,"assetType":45,"name":"Striped Emo Chained Black Tie + White Collar 3.0","creatorName":"cosmicfall","price":50,"favoriteCount":10555,"itemRestrictions":[],"foundByCategoryFilter":"None","dateCreated":"2025-05-04T19:42:43.973Z","isBundle":false,"themes":["angelcore","dark","eboy","emo","fall","grunge","light","metal","milk","softie","villain"]},{"taxonomyName":["Front Accessories"],"id":106025680770237,"assetType":45,"name":"୨୧: kawaii posed halloween ghost sleeves white","creatorName":"pawhprint","price":50,"favoriteCount":10129,"itemRestrictions":[],"foundByCategoryFilter":"None","dateCreated":"2025-10-23T17:35:31.71Z","isBundle":false,"themes":["angelcore","babycore","barbie","chibi","cutegore","dark","eboy","emo","girly","grunge","kawaii","light","milk","mini","preppy","seasonal","softgirl","softie","villain"]},{"taxonomyName":["Front Accessories"],"id":89748104984680,"assetType":45,"name":"White Jabot Neck Decoration Blue Gem [1.0]","creatorName":"Sevenly","price":50,"favoriteCount":10003,"itemRestrictions":[],"foundByCategoryFilter":"None","dateCreated":"2025-08-09T18:05:45.537Z","isBundle":false,"themes":["angelcore","light","milk","softie"]},{"taxonomyName":["Front Accessories"],"id":99797173833589,"assetType":45,"name":"black plaid emo winter scarf 3.0.","creatorName":"Odysseys","price":50,"favoriteCount":9839,"itemRestrictions":[],"foundByCategoryFilter":"None","dateCreated":"2025-08-12T02:08:29.637Z","isBundle":false,"themes":["angelcore","dark","eboy","emo","grunge","light","milk","seasonal","softie","villain","winter"]},{"taxonomyName":["Front Accessories"],"id":132055969092497,"assetType":45,"name":"♡ pink cute kawaii flowy doll dress ","creatorName":"soniico","price":50,"favoriteCount":9681,"itemRestrictions":[],"foundByCategoryFilter":"None","dateCreated":"2025-02-12T21:11:51.24Z","isBundle":false,"themes":["angelcore","babycore","barbie","bohemian","chibi","cutegore","dark","eboy","emo","formal","girly","grunge","highfashion","kawaii","light","milk","mini","preppy","softgirl","softie","villain"]}]}