{"theme":"all","page":724,"pageSize":30,"total":22155,"items":[{"id":5312192165,"itemType":"Asset","assetType":2,"bundleType":null,"name":"tee","description":"tshiurt","creatorType":"Group","creatorTargetId":6973942,"creatorName":"The Joes ;)","price":100,"priceStatus":null,"favoriteCount":0,"purchaseCount":0,"productId":6458543968163696,"saleLocationType":"ShopAndAllExperiences","collectibleItemId":"005fa744-fe08-4b16-82dd-fdb5e8f105c0","hasResellers":false,"isLimited":false,"isLimitedUnique":false,"category":"clothing","subtype":"tshirts","themes":["ownstyle"],"searchText":"tee tshiurt the joes ;) clothing tshirts ownstyle"},{"id":109143585859810,"itemType":"Asset","assetType":2,"bundleType":null,"name":"tee","description":"T-Shirt","creatorType":"User","creatorTargetId":2757644295,"creatorName":"cupidkiIl","price":1000,"priceStatus":null,"favoriteCount":0,"purchaseCount":0,"productId":2959908851970199,"saleLocationType":"ShopAndAllExperiences","collectibleItemId":"22de7c8f-3813-4fa8-858b-fe002227f68f","hasResellers":false,"isLimited":false,"isLimitedUnique":false,"category":"clothing","subtype":"tshirts","themes":["ownstyle"],"searchText":"tee t-shirt cupidkiil clothing tshirts ownstyle"},{"id":84968217975498,"itemType":"Asset","assetType":2,"bundleType":null,"name":"tee","description":"tee","creatorType":"User","creatorTargetId":716762209,"creatorName":"44lxes","price":125,"priceStatus":null,"favoriteCount":0,"purchaseCount":0,"productId":4921353027632251,"saleLocationType":"ShopAndAllExperiences","collectibleItemId":"0d493cff-58f6-4ec7-af9c-90c156607192","hasResellers":false,"isLimited":false,"isLimitedUnique":false,"category":"clothing","subtype":"tshirts","themes":["ownstyle"],"searchText":"tee tee 44lxes clothing tshirts ownstyle"},{"id":14445154388,"itemType":"Asset","assetType":2,"bundleType":null,"name":"tee","description":"tee","creatorType":"User","creatorTargetId":1691290247,"creatorName":"Gamerockroll","price":5,"priceStatus":null,"favoriteCount":0,"purchaseCount":0,"productId":1808321004310576,"saleLocationType":"ShopAndAllExperiences","collectibleItemId":"675eddcf-40ea-482c-8b86-ffe3567bcf4f","hasResellers":false,"isLimited":false,"isLimitedUnique":false,"category":"clothing","subtype":"tshirts","themes":["ownstyle"],"searchText":"tee tee gamerockroll clothing tshirts ownstyle"},{"id":18429419722,"itemType":"Asset","assetType":2,"bundleType":null,"name":"tee","description":"T-Shirt","creatorType":"User","creatorTargetId":330532194,"creatorName":"Cykenoo","price":100000,"priceStatus":null,"favoriteCount":0,"purchaseCount":0,"productId":6999551828670862,"saleLocationType":"ShopAndAllExperiences","collectibleItemId":"a94a5b0a-60a9-4317-8722-b329935ad6b9","hasResellers":false,"isLimited":false,"isLimitedUnique":false,"category":"clothing","subtype":"tshirts","themes":["ownstyle"],"searchText":"tee t-shirt cykenoo clothing tshirts ownstyle"},{"id":12113769441,"itemType":"Asset","assetType":2,"bundleType":null,"name":"Tee","description":"New clothing asset","creatorType":"User","creatorTargetId":1013506568,"creatorName":"bloxiegirl13","price":10,"priceStatus":null,"favoriteCount":0,"purchaseCount":0,"productId":6561613976027572,"saleLocationType":"ShopAndAllExperiences","collectibleItemId":"ae9e47c7-94f4-4fe1-85e2-a947e9d554ad","hasResellers":false,"isLimited":false,"isLimitedUnique":false,"category":"clothing","subtype":"tshirts","themes":["ownstyle"],"searchText":"tee new clothing asset bloxiegirl13 clothing tshirts ownstyle"},{"id":126943243900546,"itemType":"Asset","assetType":2,"bundleType":null,"name":"Tee","description":"Tee","creatorType":"User","creatorTargetId":5790998620,"creatorName":"Mwilliams660","price":5,"priceStatus":null,"favoriteCount":0,"purchaseCount":0,"productId":7291203355559836,"saleLocationType":"ShopAndAllExperiences","collectibleItemId":"ce52b025-3f00-4cd2-adec-a6ad3779b29e","hasResellers":false,"isLimited":false,"isLimitedUnique":false,"category":"clothing","subtype":"tshirts","themes":["ownstyle"],"searchText":"tee tee mwilliams660 clothing tshirts ownstyle"},{"id":10231412148,"itemType":"Asset","assetType":2,"bundleType":null,"name":"tee","description":"New clothing asset","creatorType":"User","creatorTargetId":2888016318,"creatorName":"eliwitha3","price":5,"priceStatus":null,"favoriteCount":0,"purchaseCount":0,"productId":2027163024232023,"saleLocationType":"ShopAndAllExperiences","collectibleItemId":"aafd2da2-4236-49d5-b21d-5f79f2a7bd0a","hasResellers":false,"isLimited":false,"isLimitedUnique":false,"category":"clothing","subtype":"tshirts","themes":["ownstyle"],"searchText":"tee new clothing asset eliwitha3 clothing tshirts ownstyle"},{"id":11328200099,"itemType":"Asset","assetType":2,"bundleType":null,"name":"tee","description":"New clothing asset","creatorType":"User","creatorTargetId":34503948,"creatorName":"rihannza","price":2000,"priceStatus":null,"favoriteCount":0,"purchaseCount":0,"productId":7084925879773124,"saleLocationType":"ShopAndAllExperiences","collectibleItemId":"be49fe2d-7261-4c4c-bd18-75fe8a270ec6","hasResellers":false,"isLimited":false,"isLimitedUnique":false,"category":"clothing","subtype":"tshirts","themes":["ownstyle"],"searchText":"tee new clothing asset rihannza clothing tshirts ownstyle"},{"id":10045970806,"itemType":"Asset","assetType":2,"bundleType":null,"name":"Tee","description":"New clothing asset","creatorType":"User","creatorTargetId":763568078,"creatorName":"MatthewthemonkeyXD","price":5,"priceStatus":null,"favoriteCount":0,"purchaseCount":0,"productId":4091278096356440,"saleLocationType":"ShopAndAllExperiences","collectibleItemId":"a1d25dff-e756-4da1-a232-b3bd602fd3c9","hasResellers":false,"isLimited":false,"isLimitedUnique":false,"category":"clothing","subtype":"tshirts","themes":["emo"],"searchText":"tee new clothing asset matthewthemonkeyxd clothing tshirts emo"},{"id":8572369532,"itemType":"Asset","assetType":2,"bundleType":null,"name":"Tee","description":"Tee the tarantula is finally here! To complete ######## use a topHead , transparent pants and the accessories which are a part of le character!","creatorType":"Group","creatorTargetId":10205873,"creatorName":"WallarooStudios","price":5,"priceStatus":null,"favoriteCount":0,"purchaseCount":0,"productId":366106920324982,"saleLocationType":"ShopAndAllExperiences","collectibleItemId":"7db45ac0-b2ba-4dc9-9275-2899d26fb17c","hasResellers":false,"isLimited":false,"isLimitedUnique":false,"category":"clothing","subtype":"tshirts","themes":["cosplay"],"searchText":"tee tee the tarantula is finally here! to complete ######## use a tophead , transparent pants and the accessories which are a part of le character! wallaroostudios clothing tshirts cosplay"},{"id":11962986357,"itemType":"Asset","assetType":2,"bundleType":null,"name":"Tee","description":"New clothing asset","creatorType":"User","creatorTargetId":4173409528,"creatorName":"Rip_Myth1kAce","price":10,"priceStatus":null,"favoriteCount":0,"purchaseCount":0,"productId":7618709466994564,"saleLocationType":"ShopAndAllExperiences","collectibleItemId":"64dd6b78-b5f7-4b27-a210-66f5ac9ace92","hasResellers":false,"isLimited":false,"isLimitedUnique":false,"category":"clothing","subtype":"tshirts","themes":["ownstyle"],"searchText":"tee new clothing asset rip_myth1kace clothing tshirts ownstyle"},{"id":15742897857,"itemType":"Asset","assetType":2,"bundleType":null,"name":"Tee","description":"Tee","creatorType":"User","creatorTargetId":2343438065,"creatorName":"DJsuperman08","price":10,"priceStatus":null,"favoriteCount":0,"purchaseCount":0,"productId":7465859154720001,"saleLocationType":"ShopAndAllExperiences","collectibleItemId":"5a1dfa23-77f3-4ae1-9457-627089e9d93d","hasResellers":false,"isLimited":false,"isLimitedUnique":false,"category":"clothing","subtype":"tshirts","themes":["ownstyle"],"searchText":"tee tee djsuperman08 clothing tshirts ownstyle"},{"id":18115761556,"itemType":"Asset","assetType":2,"bundleType":null,"name":"tee","description":"T-Shirt","creatorType":"User","creatorTargetId":3062367241,"creatorName":"qoilolt","price":10,"priceStatus":null,"favoriteCount":0,"purchaseCount":0,"productId":2507784981396483,"saleLocationType":"ShopAndAllExperiences","collectibleItemId":"b2327d53-f201-4d22-9116-1e9f9165f80b","hasResellers":false,"isLimited":false,"isLimitedUnique":false,"category":"clothing","subtype":"tshirts","themes":["ownstyle"],"searchText":"tee t-shirt qoilolt clothing tshirts ownstyle"},{"id":7568765392,"itemType":"Asset","assetType":2,"bundleType":null,"name":"tee","description":"New clothing asset","creatorType":"User","creatorTargetId":322238335,"creatorName":"lopezlyzander123","price":768,"priceStatus":null,"favoriteCount":0,"purchaseCount":0,"productId":4303274541414816,"saleLocationType":"ShopAndAllExperiences","collectibleItemId":"07d79988-0cc0-47b3-9566-53a4399fafc7","hasResellers":false,"isLimited":false,"isLimitedUnique":false,"category":"clothing","subtype":"tshirts","themes":["ownstyle"],"searchText":"tee new clothing asset lopezlyzander123 clothing tshirts ownstyle"},{"id":8003889590,"itemType":"Asset","assetType":2,"bundleType":null,"name":"TEE","description":"New clothing asset","creatorType":"Group","creatorTargetId":12830286,"creatorName":"HEXAGONS CIRCUS","price":3000,"priceStatus":null,"favoriteCount":0,"purchaseCount":0,"productId":99354175350275,"saleLocationType":"ShopAndAllExperiences","collectibleItemId":"1318efc1-c98d-4d52-a52b-24879b04e9f7","hasResellers":false,"isLimited":false,"isLimitedUnique":false,"category":"clothing","subtype":"tshirts","themes":["ownstyle"],"searchText":"tee new clothing asset hexagons circus clothing tshirts ownstyle"},{"id":11651341190,"itemType":"Asset","assetType":2,"bundleType":null,"name":"tee","description":"New clothing asset","creatorType":"User","creatorTargetId":2214371394,"creatorName":"turbophoenix902","price":25,"priceStatus":null,"favoriteCount":0,"purchaseCount":0,"productId":1986774660602244,"saleLocationType":"ShopAndAllExperiences","collectibleItemId":"11e67fa4-8386-498d-950f-e47bf48ee44e","hasResellers":false,"isLimited":false,"isLimitedUnique":false,"category":"clothing","subtype":"tshirts","themes":["ownstyle"],"searchText":"tee new clothing asset turbophoenix902 clothing tshirts ownstyle"},{"id":266220123,"itemType":"Asset","assetType":2,"bundleType":null,"name":"tee","description":"Tags: Red, Orange, Yellow, Green, Blue, Cyan, Teal, Turquoise, Purple, Indigo, Violet, Lavender, Pink, Black, White, Brown, Bright, Light, Baby, Soft || Pants, Dress, Skirt, Shorts, Overalls, High, Waisted, Jeans, Swimsuit, Bikini Shirt, Tang, Top, Cami, Camisole, Tank, Tee, Tube, Top, Strapless, Jacket, Sweater, Sweatshirt, Cardigan, Off, The, Shoulder, Long, Sleeved, -, || Accessories, Shoes, Uggs, Boots, Sandals, Vans, Converse, Belt, Scarf || Textured, Print, Knit, Lace, Denim, Silk, Velvet, Leather, Cheetah, Cow, Giraffe, Zebra, Tiger, Floral, Polka, Dot, Galaxy, Newspaper, Sheer, Cropped, Cut || Adjective, Adorable, Cute, Hot, Nice, Beautiful, Boy, Girl, Gilry || Users, ReesesGurl, Reese, RG, Jalki, PaperMousee, Blubaby, PlasticTurtle, iMush, MrsEnchanted, ME, Enchanted","creatorType":"Group","creatorTargetId":1030696,"creatorName":"[content deleted 1030696]","price":8,"priceStatus":null,"favoriteCount":0,"purchaseCount":0,"productId":8877719044595455,"saleLocationType":"ShopAndAllExperiences","collectibleItemId":"059f87f5-6df6-4e66-b7fd-1ab5667480bd","hasResellers":false,"isLimited":false,"isLimitedUnique":false,"category":"clothing","subtype":"tshirts","themes":["angelcore","babycore","barbie","chibi","coquette","cottagecore","cowboy","cutecore","cutegore","emo","formal","girly","gyaru","indiecore","kawaii","lolita","milk","preppy","rainbowcore","softie","uke"],"searchText":"tee tags: red, orange, yellow, green, blue, cyan, teal, turquoise, purple, indigo, violet, lavender, pink, black, white, brown, bright, light, baby, soft || pants, dress, skirt, shorts, overalls, high, waisted, jeans, swimsuit, bikini shirt, tang, top, cami, camisole, tank, tee, tube, top, strapless, jacket, sweater, sweatshirt, cardigan, off, the, shoulder, long, sleeved, -, || accessories, shoes, uggs, boots, sandals, vans, converse, belt, scarf || textured, print, knit, lace, denim, silk, velvet, leather, cheetah, cow, giraffe, zebra, tiger, floral, polka, dot, galaxy, newspaper, sheer, cropped, cut || adjective, adorable, cute, hot, nice, beautiful, boy, girl, gilry || users, reesesgurl, reese, rg, jalki, papermousee, blubaby, plasticturtle, imush, mrsenchanted, me, enchanted [content deleted 1030696] clothing tshirts angelcore babycore barbie chibi coquette cottagecore cowboy cutecore cutegore emo formal girly gyaru indiecore kawaii lolita milk preppy rainbowcore softie uke"},{"id":136224966760085,"itemType":"Asset","assetType":2,"bundleType":null,"name":"TEE","description":"T-Shirt","creatorType":"User","creatorTargetId":197580699,"creatorName":"x00u00x","price":6500,"priceStatus":null,"favoriteCount":0,"purchaseCount":0,"productId":4013827760634361,"saleLocationType":"ShopAndAllExperiences","collectibleItemId":"db3a5a79-4760-4a29-802a-b8b4267ffee0","hasResellers":false,"isLimited":false,"isLimitedUnique":false,"category":"clothing","subtype":"tshirts","themes":["ownstyle"],"searchText":"tee t-shirt x00u00x clothing tshirts ownstyle"},{"id":8503739871,"itemType":"Asset","assetType":2,"bundleType":null,"name":"tee","description":"New clothing asset","creatorType":"User","creatorTargetId":2372973292,"creatorName":"UnderCoverSWAT_Sam1k","price":5,"priceStatus":null,"favoriteCount":0,"purchaseCount":0,"productId":3482940112099154,"saleLocationType":"ShopAndAllExperiences","collectibleItemId":"ae0d0804-c65f-4634-b4ef-e3230d4712a4","hasResellers":false,"isLimited":false,"isLimitedUnique":false,"category":"clothing","subtype":"tshirts","themes":["ownstyle"],"searchText":"tee new clothing asset undercoverswat_sam1k clothing tshirts ownstyle"},{"id":86631856050540,"itemType":"Asset","assetType":2,"bundleType":null,"name":"Tee","description":"Tee","creatorType":"User","creatorTargetId":2048897099,"creatorName":"ABandur01","price":5,"priceStatus":null,"favoriteCount":0,"purchaseCount":0,"productId":5040222888578773,"saleLocationType":"ShopAndAllExperiences","collectibleItemId":"7f5038b1-df96-4f44-ae98-b5df8590b0e3","hasResellers":false,"isLimited":false,"isLimitedUnique":false,"category":"clothing","subtype":"tshirts","themes":["ownstyle"],"searchText":"tee tee abandur01 clothing tshirts ownstyle"},{"id":12219190616,"itemType":"Asset","assetType":2,"bundleType":null,"name":"tee ","description":"its a tee shirt of a drawing i made","creatorType":"Group","creatorTargetId":9002178,"creatorName":"Armyguy’s group of things","price":5,"priceStatus":null,"favoriteCount":0,"purchaseCount":0,"productId":883271453393023,"saleLocationType":"ShopAndAllExperiences","collectibleItemId":"a0a665a0-4179-4e11-9156-cd088f8c9a9f","hasResellers":false,"isLimited":false,"isLimitedUnique":false,"category":"clothing","subtype":"tshirts","themes":["ownstyle"],"searchText":"tee its a tee shirt of a drawing i made armyguy’s group of things clothing tshirts ownstyle"},{"id":2305179408,"itemType":"Asset","assetType":2,"bundleType":null,"name":"Tee","description":"THANK YOU TOO ANYONE WHO BUYS THIS <3","creatorType":"User","creatorTargetId":103417566,"creatorName":"lpstarfire12","price":5,"priceStatus":null,"favoriteCount":0,"purchaseCount":0,"productId":8981885902948811,"saleLocationType":"ShopAndAllExperiences","collectibleItemId":"68d94bd4-069d-4d01-a944-7f722717a36c","hasResellers":false,"isLimited":false,"isLimitedUnique":false,"category":"clothing","subtype":"tshirts","themes":["ownstyle"],"searchText":"tee thank you too anyone who buys this <3 lpstarfire12 clothing tshirts ownstyle"},{"id":13725790375,"itemType":"Asset","assetType":2,"bundleType":null,"name":"tee","description":"tee ","creatorType":"User","creatorTargetId":409270405,"creatorName":"emiangl","price":5,"priceStatus":null,"favoriteCount":0,"purchaseCount":0,"productId":6315302169166886,"saleLocationType":"ShopAndAllExperiences","collectibleItemId":"6d1aaa6d-7d90-46b5-90eb-dded56b0d1bc","hasResellers":false,"isLimited":false,"isLimitedUnique":false,"category":"clothing","subtype":"tshirts","themes":["ownstyle"],"searchText":"tee tee emiangl clothing tshirts ownstyle"},{"id":18977997959,"itemType":"Asset","assetType":2,"bundleType":null,"name":"tee","description":"T-Shirt","creatorType":"Group","creatorTargetId":689766,"creatorName":"Theodory","price":715,"priceStatus":null,"favoriteCount":0,"purchaseCount":0,"productId":8666857503972982,"saleLocationType":"ShopAndAllExperiences","collectibleItemId":"14e57c06-5c37-4e81-bd1b-1bd7eb50cb36","hasResellers":false,"isLimited":false,"isLimitedUnique":false,"category":"clothing","subtype":"tshirts","themes":["ownstyle"],"searchText":"tee t-shirt theodory clothing tshirts ownstyle"},{"id":12216356871,"itemType":"Asset","assetType":2,"bundleType":null,"name":"Tee","description":"New clothing asset","creatorType":"User","creatorTargetId":1491903416,"creatorName":"Hello_strangerU3U","price":100,"priceStatus":null,"favoriteCount":0,"purchaseCount":0,"productId":2831913080393092,"saleLocationType":"ShopAndAllExperiences","collectibleItemId":"1630e9e2-93bd-4774-b43e-e9f2f3876f40","hasResellers":false,"isLimited":false,"isLimitedUnique":false,"category":"clothing","subtype":"tshirts","themes":["ownstyle"],"searchText":"tee new clothing asset hello_strangeru3u clothing tshirts ownstyle"},{"id":73791636503915,"itemType":"Asset","assetType":2,"bundleType":null,"name":"Tee\n","description":"T-Shirt","creatorType":"User","creatorTargetId":2014977024,"creatorName":"buster040510","price":20,"priceStatus":null,"favoriteCount":0,"purchaseCount":0,"productId":5218791842513592,"saleLocationType":"ShopAndAllExperiences","collectibleItemId":"65637e7e-2225-48d7-8c11-bffc4a1e6aae","hasResellers":false,"isLimited":false,"isLimitedUnique":false,"category":"clothing","subtype":"tshirts","themes":["ownstyle"],"searchText":"tee t-shirt buster040510 clothing tshirts ownstyle"},{"id":18666399131,"itemType":"Asset","assetType":2,"bundleType":null,"name":"Tee","description":"T-Shirt","creatorType":"User","creatorTargetId":44542136,"creatorName":"lceChai","price":5000,"priceStatus":null,"favoriteCount":0,"purchaseCount":0,"productId":8852607191586874,"saleLocationType":"ShopAndAllExperiences","collectibleItemId":"6f77c00e-81db-4b49-9fb2-1b9eb52513ef","hasResellers":false,"isLimited":false,"isLimitedUnique":false,"category":"clothing","subtype":"tshirts","themes":["ownstyle"],"searchText":"tee t-shirt lcechai clothing tshirts ownstyle"},{"id":7164485756,"itemType":"Asset","assetType":2,"bundleType":null,"name":"tee","description":"New clothing asset","creatorType":"User","creatorTargetId":2632064966,"creatorName":"dionoxtic","price":5,"priceStatus":null,"favoriteCount":0,"purchaseCount":0,"productId":3212817845094926,"saleLocationType":"ShopAndAllExperiences","collectibleItemId":"c5006be8-0b58-49f4-b99d-a272ae17842b","hasResellers":false,"isLimited":false,"isLimitedUnique":false,"category":"clothing","subtype":"tshirts","themes":["ownstyle"],"searchText":"tee new clothing asset dionoxtic clothing tshirts ownstyle"},{"id":14592280459,"itemType":"Asset","assetType":2,"bundleType":null,"name":"Tee","description":"T-Shirt","creatorType":"User","creatorTargetId":422087880,"creatorName":"Nyecarn","price":10,"priceStatus":null,"favoriteCount":0,"purchaseCount":0,"productId":5306250223677266,"saleLocationType":"ShopAndAllExperiences","collectibleItemId":"b38d459b-84e6-4a19-b8f2-a0b69bf05c15","hasResellers":false,"isLimited":false,"isLimitedUnique":false,"category":"clothing","subtype":"tshirts","themes":["ownstyle"],"searchText":"tee t-shirt nyecarn clothing tshirts ownstyle"}]}